[
 {
  "Bir karayolu taşıtının diğer bir taşıta, yayaya, hayvana veya nesneye çarpması olayına ne ad verilir?": "Dünyada her yıl trafik kazaları nedeniyle ortalama kaç insan hayatını kaybetmektedir?",
  "Trafik Kazası": "1,3 milyon"
 },
 {
  "Bir karayolu taşıtının diğer bir taşıta, yayaya, hayvana veya nesneye çarpması olayına ne ad verilir?": "Trafik kazalarının çok büyük bir bölümüne sebep olan temel faktör nedir?",
  "Trafik Kazası": "Sürücü hatası (İnsan)"
 },
 {
  "Bir karayolu taşıtının diğer bir taşıta, yayaya, hayvana veya nesneye çarpması olayına ne ad verilir?": "Bir kazaya karışan ve yaralanmamış olan sürücülerin trafik güvenliği için yapması gereken ilk işlem nedir?",
  "Trafik Kazası": "Hemen durmak ve ışıklı işaret veya yansıtıcı cihazları koymak"
 },
 {
  "Bir karayolu taşıtının diğer bir taşıta, yayaya, hayvana veya nesneye çarpması olayına ne ad verilir?": "Ölümlü veya yaralanmalı kazalarda sorumluluğun belirlenmesi için sürücülerin uyması gereken temel yasak nedir?",
  "Trafik Kazası": "Kaza yerindeki iz ve delil niteliğindeki durumu değiştirmemek"
 },
 {
  "Bir karayolu taşıtının diğer bir taşıta, yayaya, hayvana veya nesneye çarpması olayına ne ad verilir?": "Sürücülerin kaza mahallinden ayrılmalarına izin verilen tek istisnai durum nedir?",
  "Trafik Kazası": "Yaralılara ilk yardım ve acil müdahale yaptırmak"
 },
 {
  "Bir karayolu taşıtının diğer bir taşıta, yayaya, hayvana veya nesneye çarpması olayına ne ad verilir?": "Sahibi başında bulunmayan bir araca zarar veren sürücü, ilgiliyi bulamazsa ne yapmalıdır?",
  "Trafik Kazası": "Aracın görünür bir yerine yazılı bilgi bırakmalıdır"
 },
 {
  "Bir karayolu taşıtının diğer bir taşıta, yayaya, hayvana veya nesneye çarpması olayına ne ad verilir?": "Hangi tür trafik kazalarında sürücüler yetkili çağırmadan kendi aralarında tutanak düzenleyebilir?",
  "Trafik Kazası": "Sadece maddi hasarla sonuçlanan kazalarda"
 },
 {
  "Bir karayolu taşıtının diğer bir taşıta, yayaya, hayvana veya nesneye çarpması olayına ne ad verilir?": "Maddi hasarlı kazalarda tarafların anlaşarak olay yerinden ayrılması hangi hukuki sonucu doğurur?",
  "Trafik Kazası": "Sonradan yetkililerden kaza tespit tutanağı düzenlenmesini isteyemezler"
 },
 {
  "Bir karayolu taşıtının diğer bir taşıta, yayaya, hayvana veya nesneye çarpması olayına ne ad verilir?": "Kazaya karışan araçlardan birinin sürücü belgesi yoksa tutanak kim tarafından düzenlenmelidir?",
  "Trafik Kazası": "Trafik zabıtası veya genel kolluk"
 },
 {
  "Bir karayolu taşıtının diğer bir taşıta, yayaya, hayvana veya nesneye çarpması olayına ne ad verilir?": "Sürücülerden birinde alkol veya uyuşturucu madde şüphesi varsa hangi işlem zorunludur?",
  "Trafik Kazası": "Kaza tespit tutanağının trafik zabıtası tarafından düzenlenmesi"
 },
 {
  "Bir karayolu taşıtının diğer bir taşıta, yayaya, hayvana veya nesneye çarpması olayına ne ad verilir?": "Kazaya karışan araçlardan birinin kamu kurumuna ait olması durumunda (ambulans hariç) kim tutanak tutar?",
  "Trafik Kazası": "Trafik zabıtası (polis veya jandarma)"
 },
 {
  "Bir karayolu taşıtının diğer bir taşıta, yayaya, hayvana veya nesneye çarpması olayına ne ad verilir?": "Tek taraflı maddi hasarlı kazalarda tutanağı kim düzenlemek zorundadır?",
  "Trafik Kazası": "Trafik zabıtası veya genel kolluk"
 },
 {
  "Bir karayolu taşıtının diğer bir taşıta, yayaya, hayvana veya nesneye çarpması olayına ne ad verilir?": "Olay yerinden geçmekte olan sürücülerin yetkililerin isteği üzerine yerine getirmesi gereken yükümlülük nedir?",
  "Trafik Kazası": "Yaralıları en yakın sağlık kuruluşuna götürmek"
 },
 {
  "Bir karayolu taşıtının diğer bir taşıta, yayaya, hayvana veya nesneye çarpması olayına ne ad verilir?": "Yerleşim birimleri dışındaki akaryakıt istasyonu işletenlerin sağlık açısından bulundurması gereken zorunluluk nedir?",
  "Trafik Kazası": "Standartlara uygun ve her an kullanılabilir sağlık malzemesi bulundurmak"
 },
 {
  "Bir karayolu taşıtının diğer bir taşıta, yayaya, hayvana veya nesneye çarpması olayına ne ad verilir?": "Tamirhane veya otopark sahipleri, kaza geçirdiği belli olan araçları kime bildirmekle yükümlüdür?",
  "Trafik Kazası": "Zabıta (Emniyet birimleri)"
 },
 {
  "Bir karayolu taşıtının diğer bir taşıta, yayaya, hayvana veya nesneye çarpması olayına ne ad verilir?": "Kırmızı ışıkta geçmek trafik kazalarında hangi kusur türüne girer?",
  "Trafik Kazası": "Asli (esas) kusur"
 },
 {
  "Bir karayolu taşıtının diğer bir taşıta, yayaya, hayvana veya nesneye çarpması olayına ne ad verilir?": "Bölünmüş karayolunda karşı yönden gelen trafiğin kullanıldığı şeride girmek hangi kusur sayılır?",
  "Trafik Kazası": "Asli kusur"
 },
 {
  "Bir karayolu taşıtının diğer bir taşıta, yayaya, hayvana veya nesneye çarpması olayına ne ad verilir?": "Öndeki araca arkadan çarpmak trafik hukukuna göre nasıl değerlendirilir?",
  "Trafik Kazası": "Asli kusur sayılan hal"
 },
 {
  "Bir karayolu taşıtının diğer bir taşıta, yayaya, hayvana veya nesneye çarpması olayına ne ad verilir?": "Geçme yasağı olan yerlerde araç geçmek sürücü için hangi kusur durumunu oluşturur?",
  "Trafik Kazası": "Asli kusur"
 },
 {
  "Bir karayolu taşıtının diğer bir taşıta, yayaya, hayvana veya nesneye çarpması olayına ne ad verilir?": "Kavşaklarda geçiş önceliğine uymamak hangi kusur türü kapsamında değerlendirilir?",
  "Trafik Kazası": "Asli kusur"
 },
 {
  "Bir karayolu taşıtının diğer bir taşıta, yayaya, hayvana veya nesneye çarpması olayına ne ad verilir?": "Karayolu üzerinde zorunlu haller dışında park etmek ve gerekli tedbirleri almamak ne tür bir kusurdur?",
  "Trafik Kazası": "Asli kusur"
 },
 {
  "Bir karayolu taşıtının diğer bir taşıta, yayaya, hayvana veya nesneye çarpması olayına ne ad verilir?": "Sürücü hangi durumda temel kuralı ihlal etmesine rağmen asli kusurlu sayılmaz?",
  "Trafik Kazası": "Başka bir sürücünün kural dışı hareketi sonucu kazayı önlemek amacıyla mecbur kalmışsa"
 },
 {
  "Bir karayolu taşıtının diğer bir taşıta, yayaya, hayvana veya nesneye çarpması olayına ne ad verilir?": "2021 yılında Türkiye'de meydana gelen toplam trafik kazası sayısı yaklaşık kaçtır?",
  "Trafik Kazası": "1 milyon 186 bin 353"
 },
 {
  "Bir karayolu taşıtının diğer bir taşıta, yayaya, hayvana veya nesneye çarpması olayına ne ad verilir?": "2021 yılı verilerine göre ölümlü yaralanmalı kazaların en çok gerçekleştiği yer neresidir?",
  "Trafik Kazası": "Yerleşim yeri içi (%78,6)"
 },
 {
  "Bir karayolu taşıtının diğer bir taşıta, yayaya, hayvana veya nesneye çarpması olayına ne ad verilir?": "2021 yılı trafik kazası istatistiklerine göre hayatını kaybedenlerin en büyük grubunu kimler oluşturur?",
  "Trafik Kazası": "Sürücüler (%47,6)"
 },
 {
  "Bir karayolu taşıtının diğer bir taşıta, yayaya, hayvana veya nesneye çarpması olayına ne ad verilir?": "2021 verilerine göre trafik kazalarında ölenlerin cinsiyet dağılımında erkeklerin oranı yüzde kaçtır?",
  "Trafik Kazası": "77,2"
 },
 {
  "Bir karayolu taşıtının diğer bir taşıta, yayaya, hayvana veya nesneye çarpması olayına ne ad verilir?": "Kaza tespit tutanağında 1 numaralı alana hangi bilgiler yazılır?",
  "Trafik Kazası": "Kazanın meydana geldiği tarih ve saat"
 },
 {
  "Bir karayolu taşıtının diğer bir taşıta, yayaya, hayvana veya nesneye çarpması olayına ne ad verilir?": "Görgü tanıklarının adı, adresi ve telefon bilgileri tutanağın kaç numaralı alanına kaydedilir?",
  "Trafik Kazası": "3 numaralı alan"
 },
 {
  "Bir karayolu taşıtının diğer bir taşıta, yayaya, hayvana veya nesneye çarpması olayına ne ad verilir?": "Tutanakta 5 numaralı alan hangi bilgilerin doldurulması için ayrılmıştır?",
  "Trafik Kazası": "Kaza yapan araçların bilgileri (marka, model, plaka, şasi no)"
 },
 {
  "Bir karayolu taşıtının diğer bir taşıta, yayaya, hayvana veya nesneye çarpması olayına ne ad verilir?": "Zorunlu trafik sigortası poliçe bilgileri tutanağın kaçıncı bölümüne eklenir?",
  "Trafik Kazası": "6 numaralı alan"
 },
 {
  "Bir karayolu taşıtının diğer bir taşıta, yayaya, hayvana veya nesneye çarpması olayına ne ad verilir?": "Kaza yapan araçların hız durumu ve fren izi uzunluğu tutanağın hangi bölümüne not edilir?",
  "Trafik Kazası": "7 numaralı alan"
 },
 {
  "Bir karayolu taşıtının diğer bir taşıta, yayaya, hayvana veya nesneye çarpması olayına ne ad verilir?": "Yurt dışından gelen sürücülerin pasaport ve Yeşil Kart bilgileri tutanağın hangi alanına yazılır?",
  "Trafik Kazası": "8 numaralı alan"
 },
 {
  "Bir karayolu taşıtının diğer bir taşıta, yayaya, hayvana veya nesneye çarpması olayına ne ad verilir?": "Kaza tespit tutanağında 9 numaralı kutunun işlevi nedir?",
  "Trafik Kazası": "Araçların ilk darbeyi aldığı yerin okla gösterilmesi"
 },
 {
  "Bir karayolu taşıtının diğer bir taşıta, yayaya, hayvana veya nesneye çarpması olayına ne ad verilir?": "Çarpışma yeri, şekli ve cadde isimlerinin belirtildiği kroki tutanağın kaçıncı alanına çizilir?",
  "Trafik Kazası": "10 numaralı alan"
 },
 {
  "Bir karayolu taşıtının diğer bir taşıta, yayaya, hayvana veya nesneye çarpması olayına ne ad verilir?": "Sürücülerin kazanın oluşu ile ilgili görüşlerini beyan ettiği alan kaç numaralıdır?",
  "Trafik Kazası": "11 numaralı alan"
 },
 {
  "Bir karayolu taşıtının diğer bir taşıta, yayaya, hayvana veya nesneye çarpması olayına ne ad verilir?": "Kaza tespit tutanağının tamamlanması için 12 numaralı alanda ne yapılmalıdır?",
  "Trafik Kazası": "Sürücüler tarafından imzalanmalıdır"
 },
 {
  "Bir karayolu taşıtının diğer bir taşıta, yayaya, hayvana veya nesneye çarpması olayına ne ad verilir?": "Kaza sonrası sigorta şirketine tutanakla birlikte teslim edilmesi gereken zorunlu belgeler nelerdir?",
  "Trafik Kazası": "Ehliyet, ruhsat ve zorunlu trafik sigortası poliçesi fotokopileri"
 },
 {
  "Bir karayolu taşıtının diğer bir taşıta, yayaya, hayvana veya nesneye çarpması olayına ne ad verilir?": "Sigorta Bilgi ve Gözetim Merkezi’nin online tutanak düzenlemeye imkan veren uygulamasının adı nedir?",
  "Trafik Kazası": "Mobil Kaza Tutanağı"
 },
 {
  "Bir karayolu taşıtının diğer bir taşıta, yayaya, hayvana veya nesneye çarpması olayına ne ad verilir?": "Manevraları düzenlenen genel şartlara uymamak trafik kazalarında _____ kusur sayılır.",
  "Trafik Kazası": "Asli"
 },
 {
  "Bir karayolu taşıtının diğer bir taşıta, yayaya, hayvana veya nesneye çarpması olayına ne ad verilir?": "Trafik kazasında yaralanmayan sürücüler, trafik güvenliği için _____ veya _____ cihazları koymak zorundadır.",
  "Trafik Kazası": "Işıklı işaret \/ yansıtıcı"
 },
 {
  "Bir karayolu taşıtının diğer bir taşıta, yayaya, hayvana veya nesneye çarpması olayına ne ad verilir?": "Sürücülerin kimlik ve adreslerini bildirmesi, istendiğinde karşı tarafa _____ poliçelerini göstermesi zorunludur.",
  "Trafik Kazası": "Sigorta"
 },
 {
  "Bir karayolu taşıtının diğer bir taşıta, yayaya, hayvana veya nesneye çarpması olayına ne ad verilir?": "2021 yılında Türkiye'de meydana gelen kazaların yaklaşık %84'ü _____ hasarlı kazalardır.",
  "Trafik Kazası": "Maddi"
 },
 {
  "Bir karayolu taşıtının diğer bir taşıta, yayaya, hayvana veya nesneye çarpması olayına ne ad verilir?": "Kaza tespit tutanağında araçların marka, model ve şasi numarası _____ numaralı alana yazılır.",
  "Trafik Kazası": 5
 },
 {
  "Bir karayolu taşıtının diğer bir taşıta, yayaya, hayvana veya nesneye çarpması olayına ne ad verilir?": "Ülkemizde geçerli zorunlu mali sorumluluk sigortası olmayan bir aracın kazaya karışması durumunda tutanağı _____ tutar.",
  "Trafik Kazası": "Zabıt (Polis\/Jandarma)"
 },
 {
  "Bir karayolu taşıtının diğer bir taşıta, yayaya, hayvana veya nesneye çarpması olayına ne ad verilir?": "Hangi kurumun ambulans ve acil sağlık araçları kaza yaptığında trafik zabıtası çağırma zorunluluğu yoktur?",
  "Trafik Kazası": "Sağlık Bakanlığı"
 },
 {
  "Bir karayolu taşıtının diğer bir taşıta, yayaya, hayvana veya nesneye çarpması olayına ne ad verilir?": "Kaza yerindeki iz ve deliller hangi durumda değiştirilmemelidir?",
  "Trafik Kazası": "Can ve mal güvenliğini etkilemeyen tüm kazalarda"
 },
 {
  "Bir karayolu taşıtının diğer bir taşıta, yayaya, hayvana veya nesneye çarpması olayına ne ad verilir?": "Trafik kazasında hayatını kaybedenlerin cinsiyetine göre yaralanan kadınların oranı yaklaşık % kaçtır?",
  "Trafik Kazası": "29,5"
 },
 {
  "Bir karayolu taşıtının diğer bir taşıta, yayaya, hayvana veya nesneye çarpması olayına ne ad verilir?": "Asli kusur hallerinden biri olan 'Şeride tecavüz etme' ne anlama gelir?",
  "Trafik Kazası": "Kendi şeridinden çıkarak diğer şeritleri ihlal etmek"
 },
 {
  "Bir karayolu taşıtının diğer bir taşıta, yayaya, hayvana veya nesneye çarpması olayına ne ad verilir?": "Doğrultu değiştirme manevralarını yanlış yapmak hangi kusur grubundadır?",
  "Trafik Kazası": "Asli kusur"
 },
 {
  "Bir karayolu taşıtının diğer bir taşıta, yayaya, hayvana veya nesneye çarpması olayına ne ad verilir?": "Kaza tespit tutanağında TRAMER belge numarası hangi veri grubunun içindedir?",
  "Trafik Kazası": "6 numaralı poliçe bilgileri"
 },
 {
  "Bir karayolu taşıtının diğer bir taşıta, yayaya, hayvana veya nesneye çarpması olayına ne ad verilir?": "Maddi hasarlı kazalarda tutanak düzenlenirken araçlar hangi durumda taşıt yolu dışına çıkarılmalıdır?",
  "Trafik Kazası": "Anlaşma sağlandığında ve trafik akışını engellememek için mümkünse"
 },
 {
  "Bir karayolu taşıtının diğer bir taşıta, yayaya, hayvana veya nesneye çarpması olayına ne ad verilir?": "Sürücünün ehliyetinin kullandığı araç cinsi için yetersiz olması durumunda kaza tutanağını kim düzenler?",
  "Trafik Kazası": "Genel kolluk veya trafik zabıtası"
 },
 {
  "Bir karayolu taşıtının diğer bir taşıta, yayaya, hayvana veya nesneye çarpması olayına ne ad verilir?": "Bakım-onarım istasyonu sahipleri, kaza belirtisi olan araçları işlemek zorunda oldukları defterin kodu nedir?",
  "Trafik Kazası": "Ek:38"
 },
 {
  "Bir karayolu taşıtının diğer bir taşıta, yayaya, hayvana veya nesneye çarpması olayına ne ad verilir?": "Kaplamanın (yolun) dar olduğu yerlerde geçiş önceliğine uymamak _____ kusurdur.",
  "Trafik Kazası": "Asli"
 },
 {
  "Bir karayolu taşıtının diğer bir taşıta, yayaya, hayvana veya nesneye çarpması olayına ne ad verilir?": "Kazada üçüncü kişilere ait eşyaya zarar verilmişse tutanağı sürücüler kendi aralarında tutabilir mi?",
  "Trafik Kazası": "Hayır, yetkililer (zabıta) tutmalıdır"
 },
 {
  "Bir karayolu taşıtının diğer bir taşıta, yayaya, hayvana veya nesneye çarpması olayına ne ad verilir?": "Kaza tutanağında kazanın olduğu il, ilçe ve mahalle bilgileri _____ numaralı alandadır.",
  "Trafik Kazası": 2
 },
 {
  "Bir karayolu taşıtının diğer bir taşıta, yayaya, hayvana veya nesneye çarpması olayına ne ad verilir?": "Kaza tutanağı doldurulurken tarafların yanında bulundurması gereken belgeler nelerdir?",
  "Trafik Kazası": "Ehliyet, ruhsat ve sigorta poliçesi"
 },
 {
  "Bir karayolu taşıtının diğer bir taşıta, yayaya, hayvana veya nesneye çarpması olayına ne ad verilir?": "Sürücüler arasında kaza tutanağının geçerli olması için en son hangi işlem yapılmalıdır?",
  "Trafik Kazası": "Birlikte imza altına alınması"
 },
 {
  "Bir karayolu taşıtının diğer bir taşıta, yayaya, hayvana veya nesneye çarpması olayına ne ad verilir?": "Kaza tespit tutanağında yön ve sokak isimlerinin belirtildiği alan hangisidir?",
  "Trafik Kazası": "10 numaralı kroki alanı"
 },
 {
  "Bir karayolu taşıtının diğer bir taşıta, yayaya, hayvana veya nesneye çarpması olayına ne ad verilir?": "Karayolu trafik kazalarında hayatını kaybeden yayaların oranı 2021 yılında yüzde kaçtır?",
  "Trafik Kazası": "22,1"
 },
 {
  "Bir karayolu taşıtının diğer bir taşıta, yayaya, hayvana veya nesneye çarpması olayına ne ad verilir?": "Trafik zabıtasının bulunmadığı yerlerde kazaya kim müdahale ederek tutanak düzenler?",
  "Trafik Kazası": "Genel kolluk (Jandarma)"
 },
 {
  "Bir karayolu taşıtının diğer bir taşıta, yayaya, hayvana veya nesneye çarpması olayına ne ad verilir?": "Asli kusur sayılan hallerden biri olan 'arkadan çarpma' kuralının temel sebebi nedir?",
  "Trafik Kazası": "Takip mesafesine veya duruş kurallarına uymamak"
 },
 {
  "Bir karayolu taşıtının diğer bir taşıta, yayaya, hayvana veya nesneye çarpması olayına ne ad verilir?": "Kaza tespit tutanağında T.C. Kimlik numarası hangi alanda istenir?",
  "Trafik Kazası": "4 ve 6 numaralı alanlar"
 },
 {
  "Bir karayolu taşıtının diğer bir taşıta, yayaya, hayvana veya nesneye çarpması olayına ne ad verilir?": "Kazaya karışan araçların 'Kullanım Şekli' (hususi\/ticari vb.) tutanağın kaçıncı bölümündedir?",
  "Trafik Kazası": "5 numaralı alan"
 }
]